{
  "Id": 54006,
  "CodeName": "Rocketboo",
  "Name": "Rocketboo",
  "Desc": "This Bangboo accelerates for 17.5 steps when running a hundred kilometers.",
  "Rarity": 4,
  "Icon": "UI/Sprite/A1DynamicLoad/BangbooModGarage/UnPacker/BangbooRole/BangbooGarageRole15.png",
  "Stats": {
    "Stamina": 100,
    "StaminaUpragde": 10,
    "Endurance": 180,
    "HpMax": 396,
    "Hpupgrade": 471237,
    "Attack": 69,
    "AttackUpgrade": 347303,
    "BreakStun": 99,
    "ElementAbnormalPower": 119,
    "Defence": 30,
    "DefUpgrade": 85729,
    "Crit": 500,
    "PenRatio": 0,
    "CritDmg": 5000
  },
  "Level": {
    "1": {
      "HpMax": 0,
      "Attack": 0,
      "Defence": 0,
      "LevelMax": 10,
      "LevelMin": 0,
      "Materials": { "10": 15000, "102010": 4 },
      "Extra": {
        "20101": {
          "Prop": 20101,
          "Name": "CRIT Rate",
          "Format": "{0:0.#%}",
          "Value": 0
        },
        "21101": {
          "Prop": 21101,
          "Name": "CRIT DMG",
          "Format": "{0:0.#%}",
          "Value": 0
        }
      }
    },
    "2": {
      "HpMax": 207,
      "Attack": 64,
      "Defence": 38,
      "LevelMax": 20,
      "LevelMin": 10,
      "Materials": { "10": 35000, "102020": 12 },
      "Extra": {
        "20101": {
          "Prop": 20101,
          "Name": "CRIT Rate",
          "Format": "{0:0.#%}",
          "Value": 450
        },
        "21101": {
          "Prop": 21101,
          "Name": "CRIT DMG",
          "Format": "{0:0.#%}",
          "Value": 0
        }
      }
    },
    "3": {
      "HpMax": 414,
      "Attack": 321,
      "Defence": 75,
      "LevelMax": 30,
      "LevelMin": 20,
      "Materials": { "10": 75000, "102020": 20 },
      "Extra": {
        "20101": {
          "Prop": 20101,
          "Name": "CRIT Rate",
          "Format": "{0:0.#%}",
          "Value": 2250
        },
        "21101": {
          "Prop": 21101,
          "Name": "CRIT DMG",
          "Format": "{0:0.#%}",
          "Value": 0
        }
      }
    },
    "4": {
      "HpMax": 621,
      "Attack": 963,
      "Defence": 113,
      "LevelMax": 40,
      "LevelMin": 30,
      "Materials": { "10": 125000, "102030": 10 },
      "Extra": {
        "20101": {
          "Prop": 20101,
          "Name": "CRIT Rate",
          "Format": "{0:0.#%}",
          "Value": 2250
        },
        "21101": {
          "Prop": 21101,
          "Name": "CRIT DMG",
          "Format": "{0:0.#%}",
          "Value": 2500
        }
      }
    },
    "5": {
      "HpMax": 828,
      "Attack": 2569,
      "Defence": 151,
      "LevelMax": 50,
      "LevelMin": 40,
      "Materials": { "10": 250000, "102030": 20 },
      "Extra": {
        "20101": {
          "Prop": 20101,
          "Name": "CRIT Rate",
          "Format": "{0:0.#%}",
          "Value": 4500
        },
        "21101": {
          "Prop": 21101,
          "Name": "CRIT DMG",
          "Format": "{0:0.#%}",
          "Value": 2500
        }
      }
    },
    "6": {
      "HpMax": 1034,
      "Attack": 6423,
      "Defence": 188,
      "LevelMax": 60,
      "LevelMin": 50,
      "Materials": {},
      "Extra": {
        "20101": {
          "Prop": 20101,
          "Name": "CRIT Rate",
          "Format": "{0:0.#%}",
          "Value": 4500
        },
        "21101": {
          "Prop": 21101,
          "Name": "CRIT DMG",
          "Format": "{0:0.#%}",
          "Value": 5000
        }
      }
    }
  },
  "Skill": {
    "A": {
      "Level": {
        "1": {
          "Name": "Boom!",
          "Desc": "<color=#FFFFFF>Active Skill</color>\nMounts a rocket and charges at the target. Upon hitting a target, the rocket will explode, dealing <color=#FF5521>Fire DMG</color> to enemies within range and accumulating <color=#FF5521>Fire Anomaly Buildup</color>.",
          "Property": ["DMG Multiplier", "Daze Multiplier", "Cooldown"],
          "Param": "{Skill:5400601, Prop:1001}|{Skill:5400601, Prop:1002}|18s"
        },
        "2": {
          "Name": "Boom!",
          "Desc": "<color=#FFFFFF>Active Skill</color>\nMounts a rocket and charges at the target. Upon hitting a target, the rocket will explode, dealing <color=#FF5521>Fire DMG</color> to enemies within range and accumulating <color=#FF5521>Fire Anomaly Buildup</color>.",
          "Property": ["DMG Multiplier", "Daze Multiplier", "Cooldown"],
          "Param": "{Skill:5400601, Prop:1001}|{Skill:5400601, Prop:1002}|18s"
        },
        "3": {
          "Name": "Boom!",
          "Desc": "<color=#FFFFFF>Active Skill</color>\nMounts a rocket and charges at the target. Upon hitting a target, the rocket will explode, dealing <color=#FF5521>Fire DMG</color> to enemies within range and accumulating <color=#FF5521>Fire Anomaly Buildup</color>.",
          "Property": ["DMG Multiplier", "Daze Multiplier", "Cooldown"],
          "Param": "{Skill:5400601, Prop:1001}|{Skill:5400601, Prop:1002}|18s"
        },
        "4": {
          "Name": "Boom!",
          "Desc": "<color=#FFFFFF>Active Skill</color>\nMounts a rocket and charges at the target. Upon hitting a target, the rocket will explode, dealing <color=#FF5521>Fire DMG</color> to enemies within range and accumulating <color=#FF5521>Fire Anomaly Buildup</color>.",
          "Property": ["DMG Multiplier", "Daze Multiplier", "Cooldown"],
          "Param": "{Skill:5400601, Prop:1001}|{Skill:5400601, Prop:1002}|18s"
        },
        "5": {
          "Name": "Boom!",
          "Desc": "<color=#FFFFFF>Active Skill</color>\nMounts a rocket and charges at the target. Upon hitting a target, the rocket will explode, dealing <color=#FF5521>Fire DMG</color> to enemies within range and accumulating <color=#FF5521>Fire Anomaly Buildup</color>.",
          "Property": ["DMG Multiplier", "Daze Multiplier", "Cooldown"],
          "Param": "{Skill:5400601, Prop:1001}|{Skill:5400601, Prop:1002}|18s"
        },
        "6": {
          "Name": "Boom!",
          "Desc": "<color=#FFFFFF>Active Skill</color>\nMounts a rocket and charges at the target. Upon hitting a target, the rocket will explode, dealing <color=#FF5521>Fire DMG</color> to enemies within range and accumulating <color=#FF5521>Fire Anomaly Buildup</color>.",
          "Property": ["DMG Multiplier", "Daze Multiplier", "Cooldown"],
          "Param": "{Skill:5400601, Prop:1001}|{Skill:5400601, Prop:1002}|18s"
        },
        "7": {
          "Name": "Boom!",
          "Desc": "<color=#FFFFFF>Active Skill</color>\nMounts a rocket and charges at the target. Upon hitting a target, the rocket will explode, dealing <color=#FF5521>Fire DMG</color> to enemies within range and accumulating <color=#FF5521>Fire Anomaly Buildup</color>.",
          "Property": ["DMG Multiplier", "Daze Multiplier", "Cooldown"],
          "Param": "{Skill:5400601, Prop:1001}|{Skill:5400601, Prop:1002}|18s"
        },
        "8": {
          "Name": "Boom!",
          "Desc": "<color=#FFFFFF>Active Skill</color>\nMounts a rocket and charges at the target. Upon hitting a target, the rocket will explode, dealing <color=#FF5521>Fire DMG</color> to enemies within range and accumulating <color=#FF5521>Fire Anomaly Buildup</color>.",
          "Property": ["DMG Multiplier", "Daze Multiplier", "Cooldown"],
          "Param": "{Skill:5400601, Prop:1001}|{Skill:5400601, Prop:1002}|18s"
        },
        "9": {
          "Name": "Boom!",
          "Desc": "<color=#FFFFFF>Active Skill</color>\nMounts a rocket and charges at the target. Upon hitting a target, the rocket will explode, dealing <color=#FF5521>Fire DMG</color> to enemies within range and accumulating <color=#FF5521>Fire Anomaly Buildup</color>.",
          "Property": ["DMG Multiplier", "Daze Multiplier", "Cooldown"],
          "Param": "{Skill:5400601, Prop:1001}|{Skill:5400601, Prop:1002}|18s"
        },
        "10": {
          "Name": "Boom!",
          "Desc": "<color=#FFFFFF>Active Skill</color>\nMounts a rocket and charges at the target. Upon hitting a target, the rocket will explode, dealing <color=#FF5521>Fire DMG</color> to enemies within range and accumulating <color=#FF5521>Fire Anomaly Buildup</color>.",
          "Property": ["DMG Multiplier", "Daze Multiplier", "Cooldown"],
          "Param": "{Skill:5400601, Prop:1001}|{Skill:5400601, Prop:1002}|18s"
        }
      }
    },
    "B": {
      "Level": {
        "1": {
          "Name": "Refueling",
          "Desc": "<color=#FFFFFF>Additional Ability</color>\nWhen there are 2 or more <color=#FF5521>Fire Attribute</color> characters in your squad: <color=#FFFFFF>Bangboo Chain Attack</color> inflicts 100% more Anomaly Buildup.",
          "Property": ["Anomaly Buildup Increase"],
          "Param": "100%"
        },
        "2": {
          "Name": "Refueling",
          "Desc": "<color=#FFFFFF>Additional Ability</color>\nWhen there are 2 or more <color=#FF5521>Fire Attribute</color> characters in your squad: <color=#FFFFFF>Bangboo Chain Attack</color> inflicts 125% more Anomaly Buildup.",
          "Property": ["Anomaly Buildup Increase"],
          "Param": "125%"
        },
        "3": {
          "Name": "Refueling",
          "Desc": "<color=#FFFFFF>Additional Ability</color>\nWhen there are 2 or more <color=#FF5521>Fire Attribute</color> characters in your squad: <color=#FFFFFF>Bangboo Chain Attack</color> inflicts 150% more Anomaly Buildup.",
          "Property": ["Anomaly Buildup Increase"],
          "Param": "150%"
        },
        "4": {
          "Name": "Refueling",
          "Desc": "<color=#FFFFFF>Additional Ability</color>\nWhen there are 2 or more <color=#FF5521>Fire Attribute</color> characters in your squad: <color=#FFFFFF>Bangboo Chain Attack</color> inflicts 175% more Anomaly Buildup.",
          "Property": ["Anomaly Buildup Increase"],
          "Param": "175%"
        },
        "5": {
          "Name": "Refueling",
          "Desc": "<color=#FFFFFF>Additional Ability</color>\nWhen there are 2 or more <color=#FF5521>Fire Attribute</color> characters in your squad: <color=#FFFFFF>Bangboo Chain Attack</color> inflicts 200% more Anomaly Buildup.",
          "Property": ["Anomaly Buildup Increase"],
          "Param": "200%"
        }
      }
    },
    "C": {
      "Level": {
        "1": {
          "Name": "Ka-Boom Express Shipping",
          "Desc": "<color=#FFFFFF>Bangboo Chain Attack</color>\nMounts a rocket and charges at the target. Upon hitting a target, the rocket will explode, dealing <color=#FF5521>Fire DMG</color> to enemies in a large area and inflicting massive <color=#FF5521>Fire Anomaly Buildup</color>.",
          "Property": ["DMG Multiplier", "Daze Multiplier"],
          "Param": "{Skill:5400602, Prop:1001}|{Skill:5400602, Prop:1002}"
        },
        "2": {
          "Name": "Ka-Boom Express Shipping",
          "Desc": "<color=#FFFFFF>Bangboo Chain Attack</color>\nMounts a rocket and charges at the target. Upon hitting a target, the rocket will explode, dealing <color=#FF5521>Fire DMG</color> to enemies in a large area and inflicting massive <color=#FF5521>Fire Anomaly Buildup</color>.",
          "Property": ["DMG Multiplier", "Daze Multiplier"],
          "Param": "{Skill:5400602, Prop:1001}|{Skill:5400602, Prop:1002}"
        },
        "3": {
          "Name": "Ka-Boom Express Shipping",
          "Desc": "<color=#FFFFFF>Bangboo Chain Attack</color>\nMounts a rocket and charges at the target. Upon hitting a target, the rocket will explode, dealing <color=#FF5521>Fire DMG</color> to enemies in a large area and inflicting massive <color=#FF5521>Fire Anomaly Buildup</color>.",
          "Property": ["DMG Multiplier", "Daze Multiplier"],
          "Param": "{Skill:5400602, Prop:1001}|{Skill:5400602, Prop:1002}"
        },
        "4": {
          "Name": "Ka-Boom Express Shipping",
          "Desc": "<color=#FFFFFF>Bangboo Chain Attack</color>\nMounts a rocket and charges at the target. Upon hitting a target, the rocket will explode, dealing <color=#FF5521>Fire DMG</color> to enemies in a large area and inflicting massive <color=#FF5521>Fire Anomaly Buildup</color>.",
          "Property": ["DMG Multiplier", "Daze Multiplier"],
          "Param": "{Skill:5400602, Prop:1001}|{Skill:5400602, Prop:1002}"
        },
        "5": {
          "Name": "Ka-Boom Express Shipping",
          "Desc": "<color=#FFFFFF>Bangboo Chain Attack</color>\nMounts a rocket and charges at the target. Upon hitting a target, the rocket will explode, dealing <color=#FF5521>Fire DMG</color> to enemies in a large area and inflicting massive <color=#FF5521>Fire Anomaly Buildup</color>.",
          "Property": ["DMG Multiplier", "Daze Multiplier"],
          "Param": "{Skill:5400602, Prop:1001}|{Skill:5400602, Prop:1002}"
        },
        "6": {
          "Name": "Ka-Boom Express Shipping",
          "Desc": "<color=#FFFFFF>Bangboo Chain Attack</color>\nMounts a rocket and charges at the target. Upon hitting a target, the rocket will explode, dealing <color=#FF5521>Fire DMG</color> to enemies in a large area and inflicting massive <color=#FF5521>Fire Anomaly Buildup</color>.",
          "Property": ["DMG Multiplier", "Daze Multiplier"],
          "Param": "{Skill:5400602, Prop:1001}|{Skill:5400602, Prop:1002}"
        },
        "7": {
          "Name": "Ka-Boom Express Shipping",
          "Desc": "<color=#FFFFFF>Bangboo Chain Attack</color>\nMounts a rocket and charges at the target. Upon hitting a target, the rocket will explode, dealing <color=#FF5521>Fire DMG</color> to enemies in a large area and inflicting massive <color=#FF5521>Fire Anomaly Buildup</color>.",
          "Property": ["DMG Multiplier", "Daze Multiplier"],
          "Param": "{Skill:5400602, Prop:1001}|{Skill:5400602, Prop:1002}"
        },
        "8": {
          "Name": "Ka-Boom Express Shipping",
          "Desc": "<color=#FFFFFF>Bangboo Chain Attack</color>\nMounts a rocket and charges at the target. Upon hitting a target, the rocket will explode, dealing <color=#FF5521>Fire DMG</color> to enemies in a large area and inflicting massive <color=#FF5521>Fire Anomaly Buildup</color>.",
          "Property": ["DMG Multiplier", "Daze Multiplier"],
          "Param": "{Skill:5400602, Prop:1001}|{Skill:5400602, Prop:1002}"
        },
        "9": {
          "Name": "Ka-Boom Express Shipping",
          "Desc": "<color=#FFFFFF>Bangboo Chain Attack</color>\nMounts a rocket and charges at the target. Upon hitting a target, the rocket will explode, dealing <color=#FF5521>Fire DMG</color> to enemies in a large area and inflicting massive <color=#FF5521>Fire Anomaly Buildup</color>.",
          "Property": ["DMG Multiplier", "Daze Multiplier"],
          "Param": "{Skill:5400602, Prop:1001}|{Skill:5400602, Prop:1002}"
        },
        "10": {
          "Name": "Ka-Boom Express Shipping",
          "Desc": "<color=#FFFFFF>Bangboo Chain Attack</color>\nMounts a rocket and charges at the target. Upon hitting a target, the rocket will explode, dealing <color=#FF5521>Fire DMG</color> to enemies in a large area and inflicting massive <color=#FF5521>Fire Anomaly Buildup</color>.",
          "Property": ["DMG Multiplier", "Daze Multiplier"],
          "Param": "{Skill:5400602, Prop:1001}|{Skill:5400602, Prop:1002}"
        }
      }
    }
  },
  "SkillProp": {
    "5400601": {
      "1001": { "Main": 57600, "Growth": 5760, "Format": "%" },
      "1002": { "Main": 21100, "Growth": 2110, "Format": "%" }
    },
    "5400602": {
      "1001": { "Main": 54300, "Growth": 5430, "Format": "%" },
      "1002": { "Main": 7800, "Growth": 780, "Format": "%" }
    }
  }
}
