{
  "weaponTypeKey": "bow",
  "base": {
    "hp": 819.855224609375,
    "atk": 20.48200035095215,
    "def": 52.052101135253906
  },
  "curves": {
    "hp": "GROW_CURVE_HP_S5",
    "atk": "GROW_CURVE_ATTACK_S5",
    "def": "GROW_CURVE_HP_S5"
  },
  "birthday": {
    "month": 6,
    "day": 16
  },
  "star": 5,
  "ascensions": [
    {
      "props": {
        "hp": 0,
        "def": 0,
        "atk": 0,
        "enerRech_": 0
      }
    },
    {
      "props": {
        "hp": 702.9517211914062,
        "def": 44.63100051879883,
        "atk": 17.5601806640625,
        "enerRech_": 0
      }
    },
    {
      "props": {
        "hp": 1202.4173583984375,
        "def": 76.34249877929688,
        "atk": 30.03714942932129,
        "enerRech_": 0.07999999821186066
      }
    },
    {
      "props": {
        "hp": 1868.37158203125,
        "def": 118.62449645996094,
        "atk": 46.67311096191406,
        "enerRech_": 0.1599999964237213
      }
    },
    {
      "props": {
        "hp": 2367.83740234375,
        "def": 150.33599853515625,
        "atk": 59.150081634521484,
        "enerRech_": 0.1599999964237213
      }
    },
    {
      "props": {
        "hp": 2867.302978515625,
        "def": 182.04750061035156,
        "atk": 71.6270523071289,
        "enerRech_": 0.23999999463558197
      }
    },
    {
      "props": {
        "hp": 3366.768798828125,
        "def": 213.75900268554688,
        "atk": 84.10401916503906,
        "enerRech_": 0.3199999928474426
      }
    }
  ]
}