{
  "weaponTypeKey": "claymore",
  "base": {
    "hp": 1029.5855712890625,
    "atk": 26.62660026550293,
    "def": 58.45391082763672
  },
  "curves": {
    "hp": "GROW_CURVE_HP_S5",
    "atk": "GROW_CURVE_ATTACK_S5",
    "def": "GROW_CURVE_HP_S5"
  },
  "birthday": {
    "month": 10,
    "day": 25
  },
  "star": 5,
  "ascensions": [
    {
      "props": {
        "hp": 0,
        "def": 0,
        "atk": 0,
        "critDMG_": 0
      }
    },
    {
      "props": {
        "hp": 882.7765502929688,
        "def": 50.12009811401367,
        "atk": 22.82823371887207,
        "critDMG_": 0
      }
    },
    {
      "props": {
        "hp": 1510.0125732421875,
        "def": 85.73175048828125,
        "atk": 39.04829406738281,
        "critDMG_": 0.09600000083446503
      }
    },
    {
      "props": {
        "hp": 2346.3271484375,
        "def": 133.2139434814453,
        "atk": 60.67504119873047,
        "critDMG_": 0.19200000166893005
      }
    },
    {
      "props": {
        "hp": 2973.563232421875,
        "def": 168.8256072998047,
        "atk": 76.89510345458984,
        "critDMG_": 0.19200000166893005
      }
    },
    {
      "props": {
        "hp": 3600.799072265625,
        "def": 204.437255859375,
        "atk": 93.11516571044922,
        "critDMG_": 0.2879999876022339
      }
    },
    {
      "props": {
        "hp": 4228.03515625,
        "def": 240.0489044189453,
        "atk": 109.3352279663086,
        "critDMG_": 0.3840000033378601
      }
    }
  ]
}