{
  "key": "Lisa",
  "ele": "electro",
  "region": "mondstadt",
  "weaponType": "catalyst",
  "birthday": {
    "month": 6,
    "day": 9
  },
  "rarity": 4,
  "lvlCurves": [
    {
      "key": "hp",
      "base": 802.3760986328125,
      "curve": "GROW_CURVE_HP_S4"
    },
    {
      "key": "atk",
      "base": 19.410720825195312,
      "curve": "GROW_CURVE_ATTACK_S4"
    },
    {
      "key": "def",
      "base": 48.069000244140625,
      "curve": "GROW_CURVE_HP_S4"
    }
  ],
  "ascensionBonus": [
    {
      "key": "hp",
      "values": [
        0,
        599.416015625,
        1025.31689453125,
        1593.1846923828125,
        2019.0855712890625,
        2444.986328125,
        2870.88720703125
      ]
    },
    {
      "key": "def",
      "values": [
        0,
        35.90999984741211,
        61.42499923706055,
        95.44499969482422,
        120.95999908447266,
        146.47500610351562,
        171.99000549316406
      ]
    },
    {
      "key": "atk",
      "values": [
        0,
        14.501141548156738,
        24.804584503173828,
        38.54250717163086,
        48.845951080322266,
        59.14939498901367,
        69.45283508300781
      ]
    },
    {
      "key": "eleMas",
      "values": [
        0,
        0,
        24,
        48,
        48,
        72,
        96
      ]
    }
  ]
}